sphinx_codelinks/__init__.py
sphinx_codelinks/cmd.py
sphinx_codelinks/config.py
sphinx_codelinks/logger.py
sphinx_codelinks/needextend_write.py
sphinx_codelinks/analyse/analyse.py
sphinx_codelinks/analyse/models.py
sphinx_codelinks/analyse/oneline_parser.py
sphinx_codelinks/analyse/projects.py
sphinx_codelinks/analyse/utils.py
sphinx_codelinks/source_discover/config.py
sphinx_codelinks/source_discover/source_discover.py
sphinx_codelinks/sphinx_extension/debug.py
sphinx_codelinks/sphinx_extension/html_wrapper.py
sphinx_codelinks/sphinx_extension/source_tracing.py
sphinx_codelinks/sphinx_extension/ub_sct.css
sphinx_codelinks/sphinx_extension/directives/src_trace.py
sphinx_codelinks-1.1.0.dist-info/entry_points.txt
sphinx_codelinks-1.1.0.dist-info/licenses/LICENSE
sphinx_codelinks-1.1.0.dist-info/WHEEL
sphinx_codelinks-1.1.0.dist-info/METADATA
sphinx_codelinks-1.1.0.dist-info/RECORD
