Metadata-Version: 2.4
Name: sphinx-codelinks
Version: 1.1.0
Summary: Fast Source Code Traceability for Sphinx-Needs
Author-email: team useblocks <info@useblocks.com>
Maintainer-email: Marco Heinemann <marco.heinemann@useblocks.com>, Jui-Wen Chen <jui-wen.chen@useblocks.com>
Requires-Python: >= 3.12
License-File: LICENSE
Requires-Dist: comment-parser>=1.2.4
Requires-Dist: gitignore-parser>=0.1.11
Requires-Dist: typer>=0.16.0
Requires-Dist: click < 8.2
Requires-Dist: jsonschema
Requires-Dist: sphinx>=7.4,<9
Requires-Dist: sphinx-needs>=4.2.0
Requires-Dist: jinja2
Requires-Dist: pygments
Requires-Dist: docutils
Requires-Dist: tree-sitter-cpp>=0.23.4
Requires-Dist: giturlparse>=0.12.0
Requires-Dist: tree-sitter-python>=0.23.6
Requires-Dist: tree-sitter~=0.25.1
Requires-Dist: tree-sitter-c-sharp>=0.23.1
Requires-Dist: tree-sitter-yaml>=0.7.1
